fmojinja/__init__.py
fmojinja/__main__.py
fmojinja/__version__.py
fmojinja/bare_makefile.py
fmojinja/bare_renderer.py
fmojinja/jinja_filters.py
fmojinja/mixin.py
fmojinja/abinitmp/__init__.py
fmojinja/abinitmp/__main__.py
fmojinja/abinitmp/auto.py
fmojinja/abinitmp/reader/__init__.py
fmojinja/abinitmp/reader/__main__.py
fmojinja/abinitmp/reader/cpf_filter.py
fmojinja/abinitmp/reader/cpf_reader.py
fmojinja/awk/__init__.py
fmojinja/awk/__main__.py
fmojinja/awk/pdb_reformer.py
fmojinja/awk/makefile/__init__.py
fmojinja/awk/makefile/__main__.py
fmojinja/awk/makefile/pdb_reformer.py
fmojinja/chpi/__init__.py
fmojinja/chpi/__main__.py
fmojinja/chpi/input.py
fmojinja/chpi/vpi.py
fmojinja/chpi/reader/__init__.py
fmojinja/chpi/reader/__main__.py
fmojinja/chpi/reader/hpi_reader.py
fmojinja/cpptraj/__init__.py
fmojinja/cpptraj/__main__.py
fmojinja/cpptraj/hbond.py
fmojinja/cpptraj/reduce_frames.py
fmojinja/cpptraj/rmsd.py
fmojinja/cpptraj/snapshot.py
fmojinja/cpptraj/split.py
fmojinja/cpptraj/test_hbond.py
fmojinja/cpptraj/test_reduce_frames.py
fmojinja/cpptraj/test_rmsd.py
fmojinja/cpptraj/test_snapshot.py
fmojinja/cpptraj/makefile/__init__.py
fmojinja/cpptraj/makefile/__main__.py
fmojinja/cpptraj/makefile/maskpdb.py
fmojinja/cpptraj/reader/__init__.py
fmojinja/cpptraj/reader/__main__.py
fmojinja/cpptraj/reader/hbond_reader.py
fmojinja/cpptraj/reader/rmsd_reader.py
fmojinja/gmx/__init__.py
fmojinja/gmx/__main__.py
fmojinja/gmx/equil.py
fmojinja/gmx/min.py
fmojinja/moebatch/__init__.py
fmojinja/moebatch/__main__.py
fmojinja/moebatch/resinfo.py
fmojinja/plip/__init__.py
fmojinja/plip/__main__.py
fmojinja/plip/makefile/__init__.py
fmojinja/plip/makefile/__main__.py
fmojinja/plip/makefile/docker.py
fmojinja/plip/reader/__init__.py
fmojinja/plip/reader/__main__.py
fmojinja/plip/reader/xml_reader.py
fmojinja/sander/__init__.py
fmojinja/sander/__main__.py
fmojinja/sander/dens.py
fmojinja/sander/equil.py
fmojinja/sander/heat.py
fmojinja/sander/min.py
fmojinja/sander/prod.py
fmojinja-0.0.20210914.dist-info/LICENSE
fmojinja-0.0.20210914.dist-info/METADATA
fmojinja-0.0.20210914.dist-info/WHEEL
fmojinja-0.0.20210914.dist-info/top_level.txt
fmojinja-0.0.20210914.dist-info/RECORD
